nomen/__init__.py
nomen/config.py
nomen/path_dict.py
nomen/version.py
nomen-0.42.dist-info/LICENSE
nomen-0.42.dist-info/METADATA
nomen-0.42.dist-info/WHEEL
nomen-0.42.dist-info/top_level.txt
nomen-0.42.dist-info/RECORD
