Metadata-Version: 2.1
Name: nomen
Version: 0.42
Summary: YAML configuration tree with command line flags.
Home-page: https://github.com/altosaar/nomen
Author: Jaan Altosaar
Author-email: j@jaan.io
Maintainer: Jaan Altosaar
Maintainer-email: j@jaan.io
License: MIT
Download-URL: https://github.com/altosaar/nomen/tarball/v0.42
Keywords: nomen,python,option,tree,nested,dict,parameter,flags
Platform: UNKNOWN
Classifier: Development Status :: 4 - Beta
Classifier: Environment :: Console
Classifier: License :: OSI Approved :: Apache Software License
Classifier: Natural Language :: English
Classifier: Operating System :: OS Independent
Classifier: Programming Language :: Python
Classifier: Programming Language :: Python :: 2.7
Requires-Dist: pyyaml
Requires-Dist: addict
